llama_index/multi_modal_llms/openai_like/__init__.py
llama_index/multi_modal_llms/openai_like/base.py
llama_index_multi_modal_llms_openai_like-0.2.1.dist-info/METADATA
llama_index_multi_modal_llms_openai_like-0.2.1.dist-info/WHEEL
llama_index_multi_modal_llms_openai_like-0.2.1.dist-info/licenses/LICENSE
llama_index_multi_modal_llms_openai_like-0.2.1.dist-info/RECORD
