Metadata-Version: 2.4
Name: llama-index-multi-modal-llms-openai-like
Version: 0.2.1
Summary: llama-index multi-modal-llms openai-like integration
Author-email: Tushar Adhatrao <tusharadhatrao@gmail.com>
License-Expression: MIT
License-File: LICENSE
Requires-Python: <4.0,>=3.9
Requires-Dist: llama-index-core<0.15,>=0.13.0
Requires-Dist: llama-index-embeddings-huggingface<0.7,>=0.6.0
Requires-Dist: llama-index-llms-openai-like<0.6,>=0.5.0
